Metadata-Version: 2.1
Name: cwepr
Version: 0.5.1
Summary: Package for handling cw-EPR data.
Home-page: https://www.cwepr.de/
Author: Mirjam Schröder, Pascal Kirchner, Till Biskup
Author-email: till@till-biskup.de
License: BSD
Project-URL: Documentation, https://docs.cwepr.de/
Project-URL: Source, https://github.com/tillbiskup/cwepr
Project-URL: Bug Tracker, https://github.com/tillbiskup/cwepr/issues
Keywords: EPR spectroscopy,data processing and analysis,reproducible science,reproducible research,good scientific practice,recipe-driven data analysis
Classifier: Programming Language :: Python :: 3
Classifier: Programming Language :: Python :: 3.7
Classifier: Programming Language :: Python :: 3.8
Classifier: Programming Language :: Python :: 3.9
Classifier: Programming Language :: Python :: 3.10
Classifier: Programming Language :: Python :: 3.11
Classifier: License :: OSI Approved :: BSD License
Classifier: Operating System :: OS Independent
Classifier: Intended Audience :: Science/Research
Classifier: Development Status :: 5 - Production/Stable
Classifier: Topic :: Scientific/Engineering
Requires-Python: >=3.7
License-File: LICENSE
Requires-Dist: aspecd >=0.9.0
Requires-Dist: numpy
Requires-Dist: scipy
Requires-Dist: matplotlib
Provides-Extra: dev
Requires-Dist: prospector[with_pyroma] ; extra == 'dev'
Requires-Dist: black ; extra == 'dev'
Provides-Extra: docs
Requires-Dist: sphinx ; extra == 'docs'
Requires-Dist: sphinx-rtd-theme ; extra == 'docs'
Requires-Dist: sphinxcontrib-bibtex ; extra == 'docs'
Requires-Dist: sphinx-multiversion ; extra == 'docs'
